pnpxai/__init__.py
pnpxai/_meta.py
pnpxai/messages.py
pnpxai/utils.py
pnpxai/core/__init__.py
pnpxai/core/_types.py
pnpxai/core/detector/__init__.py
pnpxai/core/detector/_core.py
pnpxai/core/detector/detector.py
pnpxai/core/detector/types.py
pnpxai/core/detector/utils.py
pnpxai/core/experiment/__init__.py
pnpxai/core/experiment/auto_explanation.py
pnpxai/core/experiment/cache.py
pnpxai/core/experiment/experiment.py
pnpxai/core/experiment/experiment_metrics_defaults.py
pnpxai/core/experiment/manager.py
pnpxai/core/experiment/observable.py
pnpxai/core/modality/__init__.py
pnpxai/core/modality/modality.py
pnpxai/core/recommender/__init__.py
pnpxai/core/recommender/recommender.py
pnpxai/evaluator/__init__.py
pnpxai/evaluator/metrics/__init__.py
pnpxai/evaluator/metrics/base.py
pnpxai/evaluator/metrics/complexity.py
pnpxai/evaluator/metrics/mu_fidelity.py
pnpxai/evaluator/metrics/pixel_flipping.py
pnpxai/evaluator/metrics/sensitivity.py
pnpxai/evaluator/optimizer/__init__.py
pnpxai/evaluator/optimizer/objectives.py
pnpxai/evaluator/optimizer/optimize.py
pnpxai/evaluator/optimizer/suggestor.py
pnpxai/evaluator/optimizer/types.py
pnpxai/evaluator/optimizer/utils.py
pnpxai/explainers/__init__.py
pnpxai/explainers/attention_rollout.py
pnpxai/explainers/base.py
pnpxai/explainers/deep_lift_shap.py
pnpxai/explainers/errors.py
pnpxai/explainers/full_grad.py
pnpxai/explainers/gfgp.py
pnpxai/explainers/grad_cam.py
pnpxai/explainers/grad_x_input.py
pnpxai/explainers/gradient.py
pnpxai/explainers/guided_backprop.py
pnpxai/explainers/guided_grad_cam.py
pnpxai/explainers/integrated_gradients.py
pnpxai/explainers/kernel_shap.py
pnpxai/explainers/lear.py
pnpxai/explainers/lime.py
pnpxai/explainers/lrp.py
pnpxai/explainers/smooth_grad.py
pnpxai/explainers/types.py
pnpxai/explainers/var_grad.py
pnpxai/explainers/attentions/__init__.py
pnpxai/explainers/attentions/attributions.py
pnpxai/explainers/attentions/partial_forwards.py
pnpxai/explainers/attentions/rules.py
pnpxai-0.1.4.dist-info/licenses/LICENSE
pnpxai-0.1.4.dist-info/METADATA
pnpxai-0.1.4.dist-info/WHEEL
pnpxai-0.1.4.dist-info/top_level.txt
pnpxai-0.1.4.dist-info/RECORD
