Metadata-Version: 2.4
Name: pnpxai
Version: 0.1.4
Summary: XAI Recommendation Toolkit
Home-page: https://github.com/OpenXAIProject/pnpxai
Download-URL: https://github.com/OpenXAIProject/pnpxai
Author: Team SAIL
Author-email: open.xai@gmail.com
Maintainer: Team SAIL
License: MIT License
Project-URL: Bug Tracker, https://github.com/OpenXAIProject/pnpxai/issues
Project-URL: Documentation, https://github.com/OpenXAIProject/pnpxai
Project-URL: Source Code, https://github.com/OpenXAIProject/pnpxai
Keywords: xai,plug and play,toolkit
Platform: Any
Requires-Python: >=3.8
License-File: LICENSE
Requires-Dist: pandas>1.5.0
Requires-Dist: captum>0.5.0
Requires-Dist: scikit-learn>0.20
Requires-Dist: scipy>0.7
Requires-Dist: kaleido>0.2
Requires-Dist: scikit-image>=0.12
Requires-Dist: zennit>=0.5.1
Requires-Dist: pytest>7.0.0
Requires-Dist: pyyaml>=5.2
Requires-Dist: tabulate>=0.9.0
Requires-Dist: shap>0.43
Requires-Dist: timm>=1.0.3
Requires-Dist: optuna>=3.1.0
Requires-Dist: transformers>=4.0.0
Requires-Dist: gensim>=4.0.0
Dynamic: author
Dynamic: author-email
Dynamic: description
Dynamic: description-content-type
Dynamic: download-url
Dynamic: home-page
Dynamic: keywords
Dynamic: license
Dynamic: license-file
Dynamic: maintainer
Dynamic: platform
Dynamic: project-url
Dynamic: requires-dist
Dynamic: requires-python
Dynamic: summary
